{
  "id": "0x380624A4a7e69dB1cA07deEcF764025FC224D056",
  "address": "0x380624A4a7e69dB1cA07deEcF764025FC224D056",
  "blockchain": "smartchain",
  "name": "SafeBTC",
  "website": "https://safebitcoin.io",
  "description": "SafeBTC is a token with frictionless fee redistribution and liquidity-adds on transfers.",
  "short_description": null,
  "audit_report": null,
  "explorer": "https://bscscan.com/token/0x380624A4a7e69dB1cA07deEcF764025FC224D056",
  "research": null,
  "symbol": "SAFEBTC",
  "type": "BEP20",
  "decimals": 9,
  "status": "active",
  "links": null,
  "tags": null
}