{
  "id": "0xEBBdf302c940c6bfd49C6b165f457fdb324649bc",
  "address": "0xEBBdf302c940c6bfd49C6b165f457fdb324649bc",
  "blockchain": "ethereum",
  "name": "Hydro (old)",
  "website": "https://www.projecthydro.org",
  "description": "",
  "short_description": null,
  "audit_report": null,
  "explorer": "https://etherscan.io/token/0xEBBdf302c940c6bfd49C6b165f457fdb324649bc",
  "research": null,
  "symbol": "HYDRO",
  "type": "ERC20",
  "decimals": 18,
  "status": "abandoned",
  "links": null,
  "tags": null
}