{
  "id": "0xcBc919D845f393Aa0ceD76085Fd082c8aDcE00be",
  "address": "0xcBc919D845f393Aa0ceD76085Fd082c8aDcE00be",
  "blockchain": "smartchain",
  "name": "BOSAGORA",
  "website": "https://bosagora.io",
  "description": "Contribute to making a better world with blockchain technology as a project enabler.",
  "short_description": null,
  "audit_report": null,
  "explorer": "https://bscscan.com/token/0xcBc919D845f393Aa0ceD76085Fd082c8aDcE00be",
  "research": "https://bosagora.io",
  "symbol": "BOA",
  "type": "BEP20",
  "decimals": 7,
  "status": "active",
  "links": [
    {
      "name": "github",
      "url": "https://github.com/bosagora"
    },
    {
      "name": "twitter",
      "url": "https://twitter.com/BOSAGORA1"
    },
    {
      "name": "telegram",
      "url": "https://t.me/bpf_eng"
    },
    {
      "name": "medium",
      "url": "https://medium.com/bosagora"
    }
  ],
  "tags": null
}