{
  "id": "0x1F8f123bf24849443a56eD9fC42b9265b7F3A39a",
  "address": "0x1F8f123bf24849443a56eD9fC42b9265b7F3A39a",
  "blockchain": "ethereum",
  "name": "UniTopia",
  "website": "https://unitopia.network",
  "description": "",
  "short_description": null,
  "audit_report": null,
  "explorer": "https://etherscan.io/token/0x1F8f123bf24849443a56eD9fC42b9265b7F3A39a",
  "research": null,
  "symbol": "uTOPIA",
  "type": "ERC20",
  "decimals": 18,
  "status": "abandoned",
  "links": null,
  "tags": null
}