{
  "id": "0x6f022E991ea21d26F85f6716c088e2864101dfEC",
  "address": "0x6f022E991ea21d26F85f6716c088e2864101dfEC",
  "blockchain": "ethereum",
  "name": "Hands Of Steel",
  "website": "https://handsofsteel.money",
  "description": "Our Seller Transfer Only Protocol Initiates Tax (STOP IT) actively taxes sellers while rewarding holders.",
  "short_description": null,
  "audit_report": null,
  "explorer": "https://etherscan.io/token/0x6f022E991ea21d26F85f6716c088e2864101dfEC",
  "research": null,
  "symbol": "STEEL",
  "type": "ERC20",
  "decimals": 0,
  "status": "active",
  "links": null,
  "tags": null
}