{
  "id": "0x839961692c56270b73538F9906f8736fC1DA4fA6",
  "address": "0x839961692c56270b73538F9906f8736fC1DA4fA6",
  "blockchain": "ethereum",
  "name": "CHALLENGE",
  "website": "https://www.challengeclg.com/",
  "description": "Challenge is a community driven DeFi-project by the people and for the people, the decisions and actions of CLG (governance token) are made by its community through voting to assure equity and fairness for all.",
  "short_description": null,
  "audit_report": null,
  "explorer": "https://etherscan.io/token/0x839961692c56270b73538F9906f8736fC1DA4fA6",
  "research": null,
  "symbol": "CLG",
  "type": "ERC20",
  "decimals": 18,
  "status": "active",
  "links": null,
  "tags": null
}