{
  "id": "0xf8aD7dFe656188A23e89da09506Adf7ad9290D5d",
  "address": "0xf8aD7dFe656188A23e89da09506Adf7ad9290D5d",
  "blockchain": "ethereum",
  "name": "Blocery Token",
  "website": "http://blocery.io",
  "description": "Utility token used as a medium of motivation to participate and enhance economic activities within the Blocery Food Supply Chain Ecosystem.",
  "short_description": null,
  "audit_report": null,
  "explorer": "https://etherscan.io/token/0xf8aD7dFe656188A23e89da09506Adf7ad9290D5d",
  "research": null,
  "symbol": "BLY",
  "type": "ERC20",
  "decimals": 18,
  "status": "active",
  "links": null,
  "tags": null
}