{
  "id": "0xE4F356EcCe6FbDA81eCDea2E38527e59422861C2",
  "address": "0xE4F356EcCe6FbDA81eCDea2E38527e59422861C2",
  "blockchain": "ethereum",
  "name": "BitStash",
  "website": "https://bitstash.co/",
  "description": "The BitStash (STASH) token is an asset used for trading on the BitStash Blockchain saving time and money on gas fees. By enabling cross-blockchain swaps BitStash is not only used for transactions as a payable token but also provides a open DeFi platform.",
  "short_description": null,
  "audit_report": null,
  "explorer": "https://etherscan.io/token/0xE4F356EcCe6FbDA81eCDea2E38527e59422861C2",
  "research": null,
  "symbol": "STASH",
  "type": "ERC20",
  "decimals": 8,
  "status": "active",
  "links": null,
  "tags": null
}