{
  "id": "0xa4ec83c8907888d006A37debF755ee39766f38ae",
  "address": "0xa4ec83c8907888d006A37debF755ee39766f38ae",
  "blockchain": "ethereum",
  "name": "Global Currency Unit",
  "website": "https://airdrop.globalcurrencyunit.io",
  "description": "",
  "short_description": null,
  "audit_report": null,
  "explorer": "https://etherscan.io/token/0xa4ec83c8907888d006A37debF755ee39766f38ae",
  "research": null,
  "symbol": "GCU",
  "type": "ERC20",
  "decimals": 18,
  "status": "abandoned",
  "links": null,
  "tags": null
}