{
  "id": "0x73145E8603c71FFfDC4E37E6957a6C55dB00ED23",
  "address": "0x73145E8603c71FFfDC4E37E6957a6C55dB00ED23",
  "blockchain": "ethereum",
  "name": "NaGa",
  "website": "https://nagatrade.com",
  "description": "Binary options trading platform",
  "short_description": null,
  "audit_report": null,
  "explorer": "https://etherscan.io/token/0x73145E8603c71FFfDC4E37E6957a6C55dB00ED23",
  "research": null,
  "symbol": "NLP",
  "type": "ERC20",
  "decimals": 18,
  "status": "active",
  "links": null,
  "tags": null
}