{
  "id": "0x49f941FA7f5731fe302068d79c8604C24C5E7196",
  "address": "0x49f941FA7f5731fe302068d79c8604C24C5E7196",
  "blockchain": "ethereum",
  "name": "BRR",
  "website": "https://brr.finance/",
  "description": "ha ha money printer go brr",
  "short_description": null,
  "audit_report": null,
  "explorer": "https://etherscan.io/token/0x49f941FA7f5731fe302068d79c8604C24C5E7196",
  "research": null,
  "symbol": "BRR",
  "type": "ERC20",
  "decimals": 18,
  "status": "active",
  "links": null,
  "tags": null
}