{
  "id": "0x459086F2376525BdCebA5bDDA135e4E9d3FeF5bf",
  "address": "0x459086F2376525BdCebA5bDDA135e4E9d3FeF5bf",
  "blockchain": "ethereum",
  "name": "renBCH",
  "website": "https://renproject.io/",
  "description": "renBCH is a one-for-one representation of BCH on Ethereum via RenVM.",
  "short_description": null,
  "audit_report": null,
  "explorer": "https://etherscan.io/token/0x459086F2376525BdCebA5bDDA135e4E9d3FeF5bf",
  "research": null,
  "symbol": "renBCH",
  "type": "ERC20",
  "decimals": 8,
  "status": "active",
  "links": null,
  "tags": null
}